setup.cfg
setup.py
collective/__init__.py
collective.recipe.z2testrunner.egg-info/PKG-INFO
collective.recipe.z2testrunner.egg-info/SOURCES.txt
collective.recipe.z2testrunner.egg-info/dependency_links.txt
collective.recipe.z2testrunner.egg-info/entry_points.txt
collective.recipe.z2testrunner.egg-info/namespace_packages.txt
collective.recipe.z2testrunner.egg-info/requires.txt
collective.recipe.z2testrunner.egg-info/top_level.txt
collective.recipe.z2testrunner.egg-info/zip-safe
collective/recipe/__init__.py
collective/recipe/z2testrunner/CHANGES.txt
collective/recipe/z2testrunner/README.txt
collective/recipe/z2testrunner/__init__.py
collective/recipe/z2testrunner/ctl.py
collective/recipe/z2testrunner/tests/__init__.py
collective/recipe/z2testrunner/tests/test_docs.py