Metadata-Version: 1.0
Name: collective.recipe.z2testrunner
Version: 0.3.1
Summary: zc.buildout recipe for generating zope2-based test runner
Home-page: https://svn.plone.org/svn/collective/buildout/collective.recipe.z2testrunner
Author: Rocky Burt
Author-email: rocky@serverzen.com
License: GPL
Platform: UNKNOWN
Classifier: Programming Language :: Python
Classifier: Development Status :: 4 - Beta
Classifier: Topic :: Utilities
Classifier: Environment :: Console
Classifier: Framework :: Zope2
Classifier: Framework :: Buildout
Classifier: Intended Audience :: Developers
Classifier: Natural Language :: English
Classifier: Operating System :: OS Independent 
Classifier: Programming Language :: Python
Classifier: Topic :: Software Development :: Libraries :: Python Modules
